klyne/__init__.py
klyne/client.py
klyne/collector.py
klyne/installation.py
klyne/transport.py
klyne/version.py
klyne-0.3.0.dist-info/METADATA
klyne-0.3.0.dist-info/WHEEL
klyne-0.3.0.dist-info/RECORD
