Metadata-Version: 2.4
Name: klyne
Version: 0.3.0
Summary: Lightweight Python package analytics SDK
Project-URL: Homepage, https://www.klyne.dev
Project-URL: Documentation, https://www.klyne.dev/docs
Project-URL: Repository, https://github.com/psincraian/klyne
Project-URL: Issues, https://github.com/psincraian/klyne/issues
Author-email: Klyne Team <hello@klyne.dev>
License: MIT
Keywords: analytics,metrics,package,telemetry
Classifier: Development Status :: 4 - Beta
Classifier: Intended Audience :: Developers
Classifier: License :: OSI Approved :: MIT License
Classifier: Programming Language :: Python :: 3
Classifier: Programming Language :: Python :: 3.11
Classifier: Programming Language :: Python :: 3.12
Classifier: Programming Language :: Python :: 3.13
Classifier: Programming Language :: Python :: 3.14
Classifier: Topic :: Software Development :: Libraries :: Python Modules
Classifier: Topic :: System :: Monitoring
Requires-Python: >=3.11
